<annotation>
	<folder>JPEGImages</folder>
	<filename>000274.jpg</filename>
	<path>/home/tony/darknet-master/VOCdevkit/VOC2018/JPEGImages/000274.jpg</path>
	<source>
		<database>Unknown</database>
	</source>
	<size>
		<width>1280</width>
		<height>720</height>
		<depth>3</depth>
	</size>
	<segmented>0</segmented>
	<object>
		<name>chapai</name>
		<pose>Unspecified</pose>
		<truncated>0</truncated>
		<difficult>0</difficult>
		<bndbox>
			<xmin>253</xmin>
			<ymin>268</ymin>
			<xmax>329</xmax>
			<ymax>408</ymax>
		</bndbox>
	</object>
	<object>
		<name>chapai</name>
		<pose>Unspecified</pose>
		<truncated>0</truncated>
		<difficult>0</difficult>
		<bndbox>
			<xmin>721</xmin>
			<ymin>371</ymin>
			<xmax>869</xmax>
			<ymax>478</ymax>
		</bndbox>
	</object>
	<object>
		<name>chapai</name>
		<pose>Unspecified</pose>
		<truncated>0</truncated>
		<difficult>0</difficult>
		<bndbox>
			<xmin>774</xmin>
			<ymin>244</ymin>
			<xmax>918</xmax>
			<ymax>354</ymax>
		</bndbox>
	</object>
	<object>
		<name>chapai</name>
		<pose>Unspecified</pose>
		<truncated>0</truncated>
		<difficult>0</difficult>
		<bndbox>
			<xmin>589</xmin>
			<ymin>327</ymin>
			<xmax>738</xmax>
			<ymax>442</ymax>
		</bndbox>
	</object>
	<object>
		<name>chapai</name>
		<pose>Unspecified</pose>
		<truncated>0</truncated>
		<difficult>0</difficult>
		<bndbox>
			<xmin>745</xmin>
			<ymin>99</ymin>
			<xmax>870</xmax>
			<ymax>227</ymax>
		</bndbox>
	</object>
	<object>
		<name>chapai</name>
		<pose>Unspecified</pose>
		<truncated>0</truncated>
		<difficult>0</difficult>
		<bndbox>
			<xmin>648</xmin>
			<ymin>118</ymin>
			<xmax>786</xmax>
			<ymax>300</ymax>
		</bndbox>
	</object>
	<object>
		<name>chapai</name>
		<pose>Unspecified</pose>
		<truncated>0</truncated>
		<difficult>0</difficult>
		<bndbox>
			<xmin>504</xmin>
			<ymin>175</ymin>
			<xmax>621</xmax>
			<ymax>328</ymax>
		</bndbox>
	</object>
	<object>
		<name>chapai</name>
		<pose>Unspecified</pose>
		<truncated>0</truncated>
		<difficult>0</difficult>
		<bndbox>
			<xmin>368</xmin>
			<ymin>214</ymin>
			<xmax>482</xmax>
			<ymax>373</ymax>
		</bndbox>
	</object>
</annotation>
