<annotation>
	<folder>JPEGImages</folder>
	<filename>000410.jpg</filename>
	<path>/home/tony/darknet-master/VOCdevkit/VOC2018/JPEGImages/000410.jpg</path>
	<source>
		<database>Unknown</database>
	</source>
	<size>
		<width>1280</width>
		<height>720</height>
		<depth>3</depth>
	</size>
	<segmented>0</segmented>
	<object>
		<name>chapai</name>
		<pose>Unspecified</pose>
		<truncated>1</truncated>
		<difficult>0</difficult>
		<bndbox>
			<xmin>527</xmin>
			<ymin>1</ymin>
			<xmax>883</xmax>
			<ymax>624</ymax>
		</bndbox>
	</object>
	<object>
		<name>chakong</name>
		<pose>Unspecified</pose>
		<truncated>0</truncated>
		<difficult>0</difficult>
		<bndbox>
			<xmin>558</xmin>
			<ymin>44</ymin>
			<xmax>642</xmax>
			<ymax>109</ymax>
		</bndbox>
	</object>
	<object>
		<name>chakong</name>
		<pose>Unspecified</pose>
		<truncated>0</truncated>
		<difficult>0</difficult>
		<bndbox>
			<xmin>705</xmin>
			<ymin>441</ymin>
			<xmax>789</xmax>
			<ymax>506</ymax>
		</bndbox>
	</object>
	<object>
		<name>chakong</name>
		<pose>Unspecified</pose>
		<truncated>0</truncated>
		<difficult>0</difficult>
		<bndbox>
			<xmin>674</xmin>
			<ymin>360</ymin>
			<xmax>758</xmax>
			<ymax>425</ymax>
		</bndbox>
	</object>
	<object>
		<name>chakong</name>
		<pose>Unspecified</pose>
		<truncated>0</truncated>
		<difficult>0</difficult>
		<bndbox>
			<xmin>650</xmin>
			<ymin>282</ymin>
			<xmax>734</xmax>
			<ymax>347</ymax>
		</bndbox>
	</object>
	<object>
		<name>chakong</name>
		<pose>Unspecified</pose>
		<truncated>0</truncated>
		<difficult>0</difficult>
		<bndbox>
			<xmin>619</xmin>
			<ymin>203</ymin>
			<xmax>703</xmax>
			<ymax>268</ymax>
		</bndbox>
	</object>
	<object>
		<name>chakong</name>
		<pose>Unspecified</pose>
		<truncated>0</truncated>
		<difficult>0</difficult>
		<bndbox>
			<xmin>582</xmin>
			<ymin>123</ymin>
			<xmax>666</xmax>
			<ymax>188</ymax>
		</bndbox>
	</object>
</annotation>
