<annotation>
	<folder>JPEGImages</folder>
	<filename>000569.jpg</filename>
	<path>/home/tony/darknet-master/VOCdevkit/VOC2018/JPEGImages/000569.jpg</path>
	<source>
		<database>Unknown</database>
	</source>
	<size>
		<width>1280</width>
		<height>720</height>
		<depth>3</depth>
	</size>
	<segmented>0</segmented>
	<object>
		<name>chatou</name>
		<pose>Unspecified</pose>
		<truncated>0</truncated>
		<difficult>0</difficult>
		<bndbox>
			<xmin>473</xmin>
			<ymin>209</ymin>
			<xmax>913</xmax>
			<ymax>695</ymax>
		</bndbox>
	</object>
	<object>
		<name>tiepian</name>
		<pose>Unspecified</pose>
		<truncated>0</truncated>
		<difficult>0</difficult>
		<bndbox>
			<xmin>565</xmin>
			<ymin>219</ymin>
			<xmax>672</xmax>
			<ymax>413</ymax>
		</bndbox>
	</object>
	<object>
		<name>tiepian</name>
		<pose>Unspecified</pose>
		<truncated>0</truncated>
		<difficult>0</difficult>
		<bndbox>
			<xmin>703</xmin>
			<ymin>202</ymin>
			<xmax>810</xmax>
			<ymax>396</ymax>
		</bndbox>
	</object>
</annotation>
